qlet/__init__.py
qlet/comps/__init__.py
qlet/comps/qimage.py
qlet/comps/qitem.py
qlet/comps/qrow.py
qlet/comps/qtext.py
qlet-0.1.2.dist-info/LICENSE
qlet-0.1.2.dist-info/METADATA
qlet-0.1.2.dist-info/WHEEL
qlet-0.1.2.dist-info/top_level.txt
qlet-0.1.2.dist-info/RECORD
