Metadata-Version: 2.1
Name: qlet
Version: 0.1.2
Summary: Provides Qt like api for flet components
Author: Jarvis Yu
License: Apache License
Project-URL: source, https://github.com/Jarvis-Yu/qlet
Project-URL: tracker, https://github.com/Jarvis-Yu/qlet/issues
Project-URL: changelog, https://github.com/Jarvis-Yu/qlet/blob/master/CHANGELOG.md
Classifier: Development Status :: 4 - Beta
Classifier: Intended Audience :: Science/Research
Classifier: Intended Audience :: Developers
Classifier: License :: OSI Approved :: MIT License
Classifier: Programming Language :: Python
Classifier: Programming Language :: Python :: 3
Classifier: Programming Language :: Python :: 3.10
Classifier: Programming Language :: Python :: 3.11
Classifier: Programming Language :: Python :: 3.12
Classifier: Programming Language :: Python :: 3 :: Only
Classifier: Typing :: Typed
Classifier: Operating System :: Microsoft :: Windows
Classifier: Operating System :: POSIX
Classifier: Operating System :: Unix
Classifier: Operating System :: MacOS
Requires-Python: >=3.10
License-File: LICENSE
Requires-Dist: typing-extensions ==4.7.1
